comandos/__init__.py
comandos/models.py
comandos/management/__init__.py
comandos/management/commands/__init__.py
comandos/management/commands/bower.py
comandos/management/commands/db.py
comandos/management/commands/npm.py
comandos/management/commands/so.py
diagnes_comandos-1.0.4.dist-info/LICENSE
diagnes_comandos-1.0.4.dist-info/METADATA
diagnes_comandos-1.0.4.dist-info/WHEEL
diagnes_comandos-1.0.4.dist-info/top_level.txt
diagnes_comandos-1.0.4.dist-info/RECORD
