Metadata-Version: 2.1
Name: diagnes-comandos
Version: 1.0.4
Summary: Pluggable django app for managing commands
Home-page: https://bitbucket.org/diagnes/diagnes-comandos
Author: Diagnes
Author-email: anderson.bispo@gmail.com
License: MIT
Platform: UNKNOWN
Classifier: Development Status :: 4 - Beta
Classifier: Framework :: Django
Classifier: Intended Audience :: Developers
Classifier: License :: OSI Approved :: BSD License
Classifier: Operating System :: OS Independent
Classifier: Programming Language :: Python
Classifier: Programming Language :: Python :: 2.7
Classifier: Programming Language :: Python :: 3.3
